odoo/addons/account_move_line_stock_info/README.rst
odoo/addons/account_move_line_stock_info/__init__.py
odoo/addons/account_move_line_stock_info/__manifest__.py
odoo/addons/account_move_line_stock_info/i18n/account_move_line_stock_info.pot
odoo/addons/account_move_line_stock_info/i18n/ar.po
odoo/addons/account_move_line_stock_info/i18n/bs.po
odoo/addons/account_move_line_stock_info/i18n/ca.po
odoo/addons/account_move_line_stock_info/i18n/cs.po
odoo/addons/account_move_line_stock_info/i18n/cs_CZ.po
odoo/addons/account_move_line_stock_info/i18n/de.po
odoo/addons/account_move_line_stock_info/i18n/en_GB.po
odoo/addons/account_move_line_stock_info/i18n/es.po
odoo/addons/account_move_line_stock_info/i18n/es_CR.po
odoo/addons/account_move_line_stock_info/i18n/es_EC.po
odoo/addons/account_move_line_stock_info/i18n/es_MX.po
odoo/addons/account_move_line_stock_info/i18n/fi.po
odoo/addons/account_move_line_stock_info/i18n/fr.po
odoo/addons/account_move_line_stock_info/i18n/fr_CH.po
odoo/addons/account_move_line_stock_info/i18n/gl.po
odoo/addons/account_move_line_stock_info/i18n/hr.po
odoo/addons/account_move_line_stock_info/i18n/hr_HR.po
odoo/addons/account_move_line_stock_info/i18n/hu.po
odoo/addons/account_move_line_stock_info/i18n/it.po
odoo/addons/account_move_line_stock_info/i18n/ja.po
odoo/addons/account_move_line_stock_info/i18n/lt.po
odoo/addons/account_move_line_stock_info/i18n/mk.po
odoo/addons/account_move_line_stock_info/i18n/mn.po
odoo/addons/account_move_line_stock_info/i18n/nb.po
odoo/addons/account_move_line_stock_info/i18n/nb_NO.po
odoo/addons/account_move_line_stock_info/i18n/nl.po
odoo/addons/account_move_line_stock_info/i18n/nl_BE.po
odoo/addons/account_move_line_stock_info/i18n/nl_NL.po
odoo/addons/account_move_line_stock_info/i18n/pt.po
odoo/addons/account_move_line_stock_info/i18n/pt_BR.po
odoo/addons/account_move_line_stock_info/i18n/pt_PT.po
odoo/addons/account_move_line_stock_info/i18n/ro.po
odoo/addons/account_move_line_stock_info/i18n/ru.po
odoo12_addon_account_move_line_stock_info-12.0.1.0.0.99.dev12.dist-info/METADATA
odoo12_addon_account_move_line_stock_info-12.0.1.0.0.99.dev12.dist-info/WHEEL
odoo12_addon_account_move_line_stock_info-12.0.1.0.0.99.dev12.dist-info/top_level.txt
odoo12_addon_account_move_line_stock_info-12.0.1.0.0.99.dev12.dist-info/RECORD
